local_tracing/__init__.py
local_tracing/mitm_tracer.py
local_tracing/trace_cleaner.py
one_shot_bench/Makefile
one_shot_bench/cli.py
one_shot_bench/common.sh
one_shot_bench/convert_old_task.py
one_shot_bench/evaluate_run.py
one_shot_bench/no.sh
one_shot_bench/prepare_task_for_eval.py
one_shot_bench/run_parallel_tasks.sh
one_shot_bench/run_parallel_tasks_simple.sh
one_shot_bench/run_sandbox.sh
one_shot_bench/run_sequential_tasks.sh
one_shot_bench/watchdog.py
one_shot_bench/hf/__init__.py
one_shot_bench/hf/export.py
one_shot_bench/hf/runner.py
one_shot_bench/hf/upload.py
one_shot_bench/hf/utils.py
one_shot_bench/task_creation/__init__.py
one_shot_bench/task_creation/git.py
one_shot_bench/task_creation/readiness.py
one_shot_bench/task_creation/task_manager.py
one_shot_bench/task_creation/traces.py
synth_bench/evaluation/__init__.py
synth_bench/evaluation/lm_rubric_scorer_structured.py
oneshot_synth-0.1.1.dist-info/METADATA
oneshot_synth-0.1.1.dist-info/WHEEL
oneshot_synth-0.1.1.dist-info/entry_points.txt
oneshot_synth-0.1.1.dist-info/licenses/LICENSE
oneshot_synth-0.1.1.dist-info/RECORD
