Metadata-Version: 2.4
Name: oneshot-synth
Version: 0.1.1
Summary: Add your description here
License-File: LICENSE
Requires-Python: >=3.11
Requires-Dist: hf>=0.0.8
Requires-Dist: huggingface-hub>=0.34.4
Requires-Dist: mitmproxy>=10.3.0
Requires-Dist: modal>=1.1.1
Requires-Dist: openai>=1.101.0
